vsui_client/__init__.py
vsui_client/_log.py
vsui_client/_main.py
vsui_client/_oo_interface.py
vsui_client/_vsui_client.py
vsui_client-1.1.9.dist-info/METADATA
vsui_client-1.1.9.dist-info/WHEEL
vsui_client-1.1.9.dist-info/RECORD
