Metadata-Version: 2.1
Name: vsui-client
Version: 1.1.9
Summary: Client module for connecting to Volume Segmantics User Inteface
Author: Matthew Pimblott
Author-email: matthew.pimblott@diamond.ac.uk
Requires-Python: >=3.9,<4.0
Classifier: Programming Language :: Python :: 3
Classifier: Programming Language :: Python :: 3.9
Classifier: Programming Language :: Python :: 3.10
Classifier: Programming Language :: Python :: 3.11
Requires-Dist: matplotlib (>=3.6.1,<4.0.0)
Requires-Dist: python-socketio[client] (>=5.7.2,<6.0.0)
